LICENSE
MANIFEST.in
README.rst
setup.cfg
setup.py
scsgate/__init__.py
scsgate/connection.py
scsgate/messages.py
scsgate/reactor.py
scsgate/tasks.py
scsgate.egg-info/PKG-INFO
scsgate.egg-info/SOURCES.txt
scsgate.egg-info/dependency_links.txt
scsgate.egg-info/entry_points.txt
scsgate.egg-info/requires.txt
scsgate.egg-info/top_level.txt
scsgate/monitor/__init__.py