Metadata-Version: 1.1
Name: scsgate
Version: 0.1.0
Summary: A Python module to interact with SCSGate
Home-page: https://github.com/flavio/scsgate
Author: Flavio Castelli
Author-email: flavio@castelli.me
License: MIT
Download-URL: https://github.com/flavio/scsgate/archive/0.1.0.tar.gz
Keywords: scsgate home-automation development
Platform: UNKNOWN
Classifier: Development Status :: 3 - Alpha
Classifier: Intended Audience :: Developers
Classifier: License :: OSI Approved :: MIT License
Classifier: Programming Language :: Python :: 3
Classifier: Programming Language :: Python :: 3.2
Classifier: Programming Language :: Python :: 3.3
Classifier: Programming Language :: Python :: 3.4
Classifier: Programming Language :: Python :: 3.5
